{
  "type": "GROUP",
"name": "All Requests",
"path": "",
"pathFormatted": "group_missing-name--1146707516",
"stats": {
    "name": "All Requests",
    "numberOfRequests": {
        "total": 61503,
        "ok": 61503,
        "ko": 0
    },
    "minResponseTime": {
        "total": 0,
        "ok": 0,
        "ko": 0
    },
    "maxResponseTime": {
        "total": 1469,
        "ok": 1469,
        "ko": 0
    },
    "meanResponseTime": {
        "total": 4,
        "ok": 4,
        "ko": 0
    },
    "standardDeviation": {
        "total": 22,
        "ok": 22,
        "ko": 0
    },
    "percentiles1": {
        "total": 3,
        "ok": 3,
        "ko": 0
    },
    "percentiles2": {
        "total": 4,
        "ok": 4,
        "ko": 0
    },
    "percentiles3": {
        "total": 6,
        "ok": 6,
        "ko": 0
    },
    "percentiles4": {
        "total": 11,
        "ok": 11,
        "ko": 0
    },
    "group1": {
    "name": "t < 250 ms",
    "htmlName": "t < 250 ms",
    "count": 61476,
    "percentage": 100
},
    "group2": {
    "name": "250 ms <= t < 1200 ms",
    "htmlName": "t >= 250 ms <br> t < 1200 ms",
    "count": 19,
    "percentage": 0
},
    "group3": {
    "name": "t >= 1200 ms",
    "htmlName": "t >= 1200 ms",
    "count": 8,
    "percentage": 0
},
    "group4": {
    "name": "failed",
    "htmlName": "failed",
    "count": 0,
    "percentage": 0
},
    "meanNumberOfRequestsPerSecond": {
        "total": 249.0,
        "ok": 249.0,
        "ko": 0
    }
},
"contents": {
"req_validac-o-es--40002687": {
        "type": "REQUEST",
        "name": "validações",
"path": "validações",
"pathFormatted": "req_validac-o-es--40002687",
"stats": {
    "name": "validações",
    "numberOfRequests": {
        "total": 123,
        "ok": 123,
        "ko": 0
    },
    "minResponseTime": {
        "total": 0,
        "ok": 0,
        "ko": 0
    },
    "maxResponseTime": {
        "total": 1469,
        "ok": 1469,
        "ko": 0
    },
    "meanResponseTime": {
        "total": 209,
        "ok": 209,
        "ko": 0
    },
    "standardDeviation": {
        "total": 432,
        "ok": 432,
        "ko": 0
    },
    "percentiles1": {
        "total": 13,
        "ok": 13,
        "ko": 0
    },
    "percentiles2": {
        "total": 50,
        "ok": 50,
        "ko": 0
    },
    "percentiles3": {
        "total": 1266,
        "ok": 1266,
        "ko": 0
    },
    "percentiles4": {
        "total": 1465,
        "ok": 1465,
        "ko": 0
    },
    "group1": {
    "name": "t < 250 ms",
    "htmlName": "t < 250 ms",
    "count": 103,
    "percentage": 84
},
    "group2": {
    "name": "250 ms <= t < 1200 ms",
    "htmlName": "t >= 250 ms <br> t < 1200 ms",
    "count": 12,
    "percentage": 10
},
    "group3": {
    "name": "t >= 1200 ms",
    "htmlName": "t >= 1200 ms",
    "count": 8,
    "percentage": 7
},
    "group4": {
    "name": "failed",
    "htmlName": "failed",
    "count": 0,
    "percentage": 0
},
    "meanNumberOfRequestsPerSecond": {
        "total": 0.4979757085020243,
        "ok": 0.4979757085020243,
        "ko": 0
    }
}
    },"req_extratos--1809255608": {
        "type": "REQUEST",
        "name": "extratos",
"path": "extratos",
"pathFormatted": "req_extratos--1809255608",
"stats": {
    "name": "extratos",
    "numberOfRequests": {
        "total": 1860,
        "ok": 1860,
        "ko": 0
    },
    "minResponseTime": {
        "total": 1,
        "ok": 1,
        "ko": 0
    },
    "maxResponseTime": {
        "total": 102,
        "ok": 102,
        "ko": 0
    },
    "meanResponseTime": {
        "total": 4,
        "ok": 4,
        "ko": 0
    },
    "standardDeviation": {
        "total": 3,
        "ok": 3,
        "ko": 0
    },
    "percentiles1": {
        "total": 4,
        "ok": 4,
        "ko": 0
    },
    "percentiles2": {
        "total": 5,
        "ok": 5,
        "ko": 0
    },
    "percentiles3": {
        "total": 7,
        "ok": 7,
        "ko": 0
    },
    "percentiles4": {
        "total": 8,
        "ok": 8,
        "ko": 0
    },
    "group1": {
    "name": "t < 250 ms",
    "htmlName": "t < 250 ms",
    "count": 1860,
    "percentage": 100
},
    "group2": {
    "name": "250 ms <= t < 1200 ms",
    "htmlName": "t >= 250 ms <br> t < 1200 ms",
    "count": 0,
    "percentage": 0
},
    "group3": {
    "name": "t >= 1200 ms",
    "htmlName": "t >= 1200 ms",
    "count": 0,
    "percentage": 0
},
    "group4": {
    "name": "failed",
    "htmlName": "failed",
    "count": 0,
    "percentage": 0
},
    "meanNumberOfRequestsPerSecond": {
        "total": 7.530364372469635,
        "ok": 7.530364372469635,
        "ko": 0
    }
}
    },"req_cre-ditos-1306955929": {
        "type": "REQUEST",
        "name": "créditos",
"path": "créditos",
"pathFormatted": "req_cre-ditos-1306955929",
"stats": {
    "name": "créditos",
    "numberOfRequests": {
        "total": 19860,
        "ok": 19860,
        "ko": 0
    },
    "minResponseTime": {
        "total": 2,
        "ok": 2,
        "ko": 0
    },
    "maxResponseTime": {
        "total": 361,
        "ok": 361,
        "ko": 0
    },
    "meanResponseTime": {
        "total": 4,
        "ok": 4,
        "ko": 0
    },
    "standardDeviation": {
        "total": 5,
        "ok": 5,
        "ko": 0
    },
    "percentiles1": {
        "total": 4,
        "ok": 4,
        "ko": 0
    },
    "percentiles2": {
        "total": 5,
        "ok": 5,
        "ko": 0
    },
    "percentiles3": {
        "total": 7,
        "ok": 7,
        "ko": 0
    },
    "percentiles4": {
        "total": 12,
        "ok": 12,
        "ko": 0
    },
    "group1": {
    "name": "t < 250 ms",
    "htmlName": "t < 250 ms",
    "count": 19857,
    "percentage": 100
},
    "group2": {
    "name": "250 ms <= t < 1200 ms",
    "htmlName": "t >= 250 ms <br> t < 1200 ms",
    "count": 3,
    "percentage": 0
},
    "group3": {
    "name": "t >= 1200 ms",
    "htmlName": "t >= 1200 ms",
    "count": 0,
    "percentage": 0
},
    "group4": {
    "name": "failed",
    "htmlName": "failed",
    "count": 0,
    "percentage": 0
},
    "meanNumberOfRequestsPerSecond": {
        "total": 80.40485829959515,
        "ok": 80.40485829959515,
        "ko": 0
    }
}
    },"req_de-bitos-1025427916": {
        "type": "REQUEST",
        "name": "débitos",
"path": "débitos",
"pathFormatted": "req_de-bitos-1025427916",
"stats": {
    "name": "débitos",
    "numberOfRequests": {
        "total": 39660,
        "ok": 39660,
        "ko": 0
    },
    "minResponseTime": {
        "total": 0,
        "ok": 0,
        "ko": 0
    },
    "maxResponseTime": {
        "total": 407,
        "ok": 407,
        "ko": 0
    },
    "meanResponseTime": {
        "total": 3,
        "ok": 3,
        "ko": 0
    },
    "standardDeviation": {
        "total": 5,
        "ok": 5,
        "ko": 0
    },
    "percentiles1": {
        "total": 3,
        "ok": 3,
        "ko": 0
    },
    "percentiles2": {
        "total": 4,
        "ok": 4,
        "ko": 0
    },
    "percentiles3": {
        "total": 6,
        "ok": 6,
        "ko": 0
    },
    "percentiles4": {
        "total": 10,
        "ok": 10,
        "ko": 0
    },
    "group1": {
    "name": "t < 250 ms",
    "htmlName": "t < 250 ms",
    "count": 39656,
    "percentage": 100
},
    "group2": {
    "name": "250 ms <= t < 1200 ms",
    "htmlName": "t >= 250 ms <br> t < 1200 ms",
    "count": 4,
    "percentage": 0
},
    "group3": {
    "name": "t >= 1200 ms",
    "htmlName": "t >= 1200 ms",
    "count": 0,
    "percentage": 0
},
    "group4": {
    "name": "failed",
    "htmlName": "failed",
    "count": 0,
    "percentage": 0
},
    "meanNumberOfRequestsPerSecond": {
        "total": 160.5668016194332,
        "ok": 160.5668016194332,
        "ko": 0
    }
}
    }
}

}