{
  "type": "GROUP",
"name": "All Requests",
"path": "",
"pathFormatted": "group_missing-name--1146707516",
"stats": {
    "name": "All Requests",
    "numberOfRequests": {
        "total": 61503,
        "ok": 61499,
        "ko": 4
    },
    "minResponseTime": {
        "total": 0,
        "ok": 0,
        "ko": 1033
    },
    "maxResponseTime": {
        "total": 1055,
        "ok": 1055,
        "ko": 1046
    },
    "meanResponseTime": {
        "total": 4,
        "ok": 4,
        "ko": 1039
    },
    "standardDeviation": {
        "total": 49,
        "ok": 48,
        "ko": 5
    },
    "percentiles1": {
        "total": 1,
        "ok": 1,
        "ko": 1039
    },
    "percentiles2": {
        "total": 2,
        "ok": 2,
        "ko": 1042
    },
    "percentiles3": {
        "total": 2,
        "ok": 2,
        "ko": 1045
    },
    "percentiles4": {
        "total": 15,
        "ok": 15,
        "ko": 1046
    },
    "group1": {
    "name": "t < 250 ms",
    "htmlName": "t < 250 ms",
    "count": 61363,
    "percentage": 100
},
    "group2": {
    "name": "250 ms <= t < 1200 ms",
    "htmlName": "t >= 250 ms <br> t < 1200 ms",
    "count": 136,
    "percentage": 0
},
    "group3": {
    "name": "t >= 1200 ms",
    "htmlName": "t >= 1200 ms",
    "count": 0,
    "percentage": 0
},
    "group4": {
    "name": "failed",
    "htmlName": "failed",
    "count": 4,
    "percentage": 0
},
    "meanNumberOfRequestsPerSecond": {
        "total": 249.0,
        "ok": 248.9838056680162,
        "ko": 0.016194331983805668
    }
},
"contents": {
"req_validac-o-es--40002687": {
        "type": "REQUEST",
        "name": "validações",
"path": "validações",
"pathFormatted": "req_validac-o-es--40002687",
"stats": {
    "name": "validações",
    "numberOfRequests": {
        "total": 123,
        "ok": 119,
        "ko": 4
    },
    "minResponseTime": {
        "total": 1,
        "ok": 1,
        "ko": 1033
    },
    "maxResponseTime": {
        "total": 1055,
        "ok": 1055,
        "ko": 1046
    },
    "meanResponseTime": {
        "total": 202,
        "ok": 173,
        "ko": 1039
    },
    "standardDeviation": {
        "total": 397,
        "ok": 372,
        "ko": 5
    },
    "percentiles1": {
        "total": 11,
        "ok": 10,
        "ko": 1039
    },
    "percentiles2": {
        "total": 31,
        "ok": 30,
        "ko": 1042
    },
    "percentiles3": {
        "total": 1041,
        "ok": 1040,
        "ko": 1045
    },
    "percentiles4": {
        "total": 1048,
        "ok": 1048,
        "ko": 1046
    },
    "group1": {
    "name": "t < 250 ms",
    "htmlName": "t < 250 ms",
    "count": 100,
    "percentage": 81
},
    "group2": {
    "name": "250 ms <= t < 1200 ms",
    "htmlName": "t >= 250 ms <br> t < 1200 ms",
    "count": 19,
    "percentage": 15
},
    "group3": {
    "name": "t >= 1200 ms",
    "htmlName": "t >= 1200 ms",
    "count": 0,
    "percentage": 0
},
    "group4": {
    "name": "failed",
    "htmlName": "failed",
    "count": 4,
    "percentage": 3
},
    "meanNumberOfRequestsPerSecond": {
        "total": 0.4979757085020243,
        "ok": 0.4817813765182186,
        "ko": 0.016194331983805668
    }
}
    },"req_extratos--1809255608": {
        "type": "REQUEST",
        "name": "extratos",
"path": "extratos",
"pathFormatted": "req_extratos--1809255608",
"stats": {
    "name": "extratos",
    "numberOfRequests": {
        "total": 1860,
        "ok": 1860,
        "ko": 0
    },
    "minResponseTime": {
        "total": 0,
        "ok": 0,
        "ko": 0
    },
    "maxResponseTime": {
        "total": 1024,
        "ok": 1024,
        "ko": 0
    },
    "meanResponseTime": {
        "total": 4,
        "ok": 4,
        "ko": 0
    },
    "standardDeviation": {
        "total": 47,
        "ok": 47,
        "ko": 0
    },
    "percentiles1": {
        "total": 2,
        "ok": 2,
        "ko": 0
    },
    "percentiles2": {
        "total": 3,
        "ok": 3,
        "ko": 0
    },
    "percentiles3": {
        "total": 3,
        "ok": 3,
        "ko": 0
    },
    "percentiles4": {
        "total": 15,
        "ok": 15,
        "ko": 0
    },
    "group1": {
    "name": "t < 250 ms",
    "htmlName": "t < 250 ms",
    "count": 1856,
    "percentage": 100
},
    "group2": {
    "name": "250 ms <= t < 1200 ms",
    "htmlName": "t >= 250 ms <br> t < 1200 ms",
    "count": 4,
    "percentage": 0
},
    "group3": {
    "name": "t >= 1200 ms",
    "htmlName": "t >= 1200 ms",
    "count": 0,
    "percentage": 0
},
    "group4": {
    "name": "failed",
    "htmlName": "failed",
    "count": 0,
    "percentage": 0
},
    "meanNumberOfRequestsPerSecond": {
        "total": 7.530364372469635,
        "ok": 7.530364372469635,
        "ko": 0
    }
}
    },"req_cre-ditos-1306955929": {
        "type": "REQUEST",
        "name": "créditos",
"path": "créditos",
"pathFormatted": "req_cre-ditos-1306955929",
"stats": {
    "name": "créditos",
    "numberOfRequests": {
        "total": 19860,
        "ok": 19860,
        "ko": 0
    },
    "minResponseTime": {
        "total": 0,
        "ok": 0,
        "ko": 0
    },
    "maxResponseTime": {
        "total": 1041,
        "ok": 1041,
        "ko": 0
    },
    "meanResponseTime": {
        "total": 4,
        "ok": 4,
        "ko": 0
    },
    "standardDeviation": {
        "total": 47,
        "ok": 47,
        "ko": 0
    },
    "percentiles1": {
        "total": 2,
        "ok": 2,
        "ko": 0
    },
    "percentiles2": {
        "total": 2,
        "ok": 2,
        "ko": 0
    },
    "percentiles3": {
        "total": 2,
        "ok": 2,
        "ko": 0
    },
    "percentiles4": {
        "total": 16,
        "ok": 16,
        "ko": 0
    },
    "group1": {
    "name": "t < 250 ms",
    "htmlName": "t < 250 ms",
    "count": 19818,
    "percentage": 100
},
    "group2": {
    "name": "250 ms <= t < 1200 ms",
    "htmlName": "t >= 250 ms <br> t < 1200 ms",
    "count": 42,
    "percentage": 0
},
    "group3": {
    "name": "t >= 1200 ms",
    "htmlName": "t >= 1200 ms",
    "count": 0,
    "percentage": 0
},
    "group4": {
    "name": "failed",
    "htmlName": "failed",
    "count": 0,
    "percentage": 0
},
    "meanNumberOfRequestsPerSecond": {
        "total": 80.40485829959515,
        "ok": 80.40485829959515,
        "ko": 0
    }
}
    },"req_de-bitos-1025427916": {
        "type": "REQUEST",
        "name": "débitos",
"path": "débitos",
"pathFormatted": "req_de-bitos-1025427916",
"stats": {
    "name": "débitos",
    "numberOfRequests": {
        "total": 39660,
        "ok": 39660,
        "ko": 0
    },
    "minResponseTime": {
        "total": 0,
        "ok": 0,
        "ko": 0
    },
    "maxResponseTime": {
        "total": 1043,
        "ok": 1043,
        "ko": 0
    },
    "meanResponseTime": {
        "total": 3,
        "ok": 3,
        "ko": 0
    },
    "standardDeviation": {
        "total": 43,
        "ok": 43,
        "ko": 0
    },
    "percentiles1": {
        "total": 1,
        "ok": 1,
        "ko": 0
    },
    "percentiles2": {
        "total": 1,
        "ok": 1,
        "ko": 0
    },
    "percentiles3": {
        "total": 2,
        "ok": 2,
        "ko": 0
    },
    "percentiles4": {
        "total": 13,
        "ok": 13,
        "ko": 0
    },
    "group1": {
    "name": "t < 250 ms",
    "htmlName": "t < 250 ms",
    "count": 39589,
    "percentage": 100
},
    "group2": {
    "name": "250 ms <= t < 1200 ms",
    "htmlName": "t >= 250 ms <br> t < 1200 ms",
    "count": 71,
    "percentage": 0
},
    "group3": {
    "name": "t >= 1200 ms",
    "htmlName": "t >= 1200 ms",
    "count": 0,
    "percentage": 0
},
    "group4": {
    "name": "failed",
    "htmlName": "failed",
    "count": 0,
    "percentage": 0
},
    "meanNumberOfRequestsPerSecond": {
        "total": 160.5668016194332,
        "ok": 160.5668016194332,
        "ko": 0
    }
}
    }
}

}