{
  "type": "GROUP",
"name": "All Requests",
"path": "",
"pathFormatted": "group_missing-name--1146707516",
"stats": {
    "name": "All Requests",
    "numberOfRequests": {
        "total": 61478,
        "ok": 49394,
        "ko": 12084
    },
    "minResponseTime": {
        "total": 0,
        "ok": 2,
        "ko": 0
    },
    "maxResponseTime": {
        "total": 4235,
        "ok": 4235,
        "ko": 3267
    },
    "meanResponseTime": {
        "total": 1140,
        "ok": 1416,
        "ko": 12
    },
    "standardDeviation": {
        "total": 1203,
        "ok": 1189,
        "ko": 49
    },
    "percentiles1": {
        "total": 753,
        "ok": 1181,
        "ko": 8
    },
    "percentiles2": {
        "total": 2200,
        "ok": 2538,
        "ko": 18
    },
    "percentiles3": {
        "total": 3293,
        "ok": 3345,
        "ko": 33
    },
    "percentiles4": {
        "total": 3601,
        "ok": 3657,
        "ko": 45
    },
    "group1": {
    "name": "t < 250 ms",
    "htmlName": "t < 250 ms",
    "count": 12437,
    "percentage": 20
},
    "group2": {
    "name": "250 ms <= t < 1200 ms",
    "htmlName": "t >= 250 ms <br> t < 1200 ms",
    "count": 12512,
    "percentage": 20
},
    "group3": {
    "name": "t >= 1200 ms",
    "htmlName": "t >= 1200 ms",
    "count": 24445,
    "percentage": 40
},
    "group4": {
    "name": "failed",
    "htmlName": "failed",
    "count": 12084,
    "percentage": 20
},
    "meanNumberOfRequestsPerSecond": {
        "total": 248.8987854251012,
        "ok": 199.9757085020243,
        "ko": 48.92307692307692
    }
},
"contents": {
"req_validac-o-es--40002687": {
        "type": "REQUEST",
        "name": "validações",
"path": "validações",
"pathFormatted": "req_validac-o-es--40002687",
"stats": {
    "name": "validações",
    "numberOfRequests": {
        "total": 98,
        "ok": 98,
        "ko": 0
    },
    "minResponseTime": {
        "total": 4,
        "ok": 4,
        "ko": 0
    },
    "maxResponseTime": {
        "total": 744,
        "ok": 744,
        "ko": 0
    },
    "meanResponseTime": {
        "total": 165,
        "ok": 165,
        "ko": 0
    },
    "standardDeviation": {
        "total": 179,
        "ok": 179,
        "ko": 0
    },
    "percentiles1": {
        "total": 96,
        "ok": 96,
        "ko": 0
    },
    "percentiles2": {
        "total": 259,
        "ok": 259,
        "ko": 0
    },
    "percentiles3": {
        "total": 559,
        "ok": 559,
        "ko": 0
    },
    "percentiles4": {
        "total": 727,
        "ok": 727,
        "ko": 0
    },
    "group1": {
    "name": "t < 250 ms",
    "htmlName": "t < 250 ms",
    "count": 72,
    "percentage": 73
},
    "group2": {
    "name": "250 ms <= t < 1200 ms",
    "htmlName": "t >= 250 ms <br> t < 1200 ms",
    "count": 26,
    "percentage": 27
},
    "group3": {
    "name": "t >= 1200 ms",
    "htmlName": "t >= 1200 ms",
    "count": 0,
    "percentage": 0
},
    "group4": {
    "name": "failed",
    "htmlName": "failed",
    "count": 0,
    "percentage": 0
},
    "meanNumberOfRequestsPerSecond": {
        "total": 0.3967611336032389,
        "ok": 0.3967611336032389,
        "ko": 0
    }
}
    },"req_extratos--1809255608": {
        "type": "REQUEST",
        "name": "extratos",
"path": "extratos",
"pathFormatted": "req_extratos--1809255608",
"stats": {
    "name": "extratos",
    "numberOfRequests": {
        "total": 1860,
        "ok": 1284,
        "ko": 576
    },
    "minResponseTime": {
        "total": 0,
        "ok": 5,
        "ko": 0
    },
    "maxResponseTime": {
        "total": 4235,
        "ok": 4235,
        "ko": 52
    },
    "meanResponseTime": {
        "total": 886,
        "ok": 1283,
        "ko": 2
    },
    "standardDeviation": {
        "total": 1177,
        "ok": 1224,
        "ko": 4
    },
    "percentiles1": {
        "total": 120,
        "ok": 966,
        "ko": 1
    },
    "percentiles2": {
        "total": 1526,
        "ok": 2422,
        "ko": 2
    },
    "percentiles3": {
        "total": 3245,
        "ok": 3347,
        "ko": 6
    },
    "percentiles4": {
        "total": 3603,
        "ok": 3829,
        "ko": 22
    },
    "group1": {
    "name": "t < 250 ms",
    "htmlName": "t < 250 ms",
    "count": 417,
    "percentage": 22
},
    "group2": {
    "name": "250 ms <= t < 1200 ms",
    "htmlName": "t >= 250 ms <br> t < 1200 ms",
    "count": 296,
    "percentage": 16
},
    "group3": {
    "name": "t >= 1200 ms",
    "htmlName": "t >= 1200 ms",
    "count": 571,
    "percentage": 31
},
    "group4": {
    "name": "failed",
    "htmlName": "failed",
    "count": 576,
    "percentage": 31
},
    "meanNumberOfRequestsPerSecond": {
        "total": 7.530364372469635,
        "ok": 5.198380566801619,
        "ko": 2.331983805668016
    }
}
    },"req_de-bitos-1025427916": {
        "type": "REQUEST",
        "name": "débitos",
"path": "débitos",
"pathFormatted": "req_de-bitos-1025427916",
"stats": {
    "name": "débitos",
    "numberOfRequests": {
        "total": 39660,
        "ok": 32733,
        "ko": 6927
    },
    "minResponseTime": {
        "total": 0,
        "ok": 2,
        "ko": 0
    },
    "maxResponseTime": {
        "total": 4233,
        "ok": 4233,
        "ko": 3267
    },
    "meanResponseTime": {
        "total": 1186,
        "ok": 1434,
        "ko": 14
    },
    "standardDeviation": {
        "total": 1205,
        "ok": 1186,
        "ko": 50
    },
    "percentiles1": {
        "total": 878,
        "ok": 1208,
        "ko": 11
    },
    "percentiles2": {
        "total": 2291,
        "ok": 2556,
        "ko": 20
    },
    "percentiles3": {
        "total": 3299,
        "ok": 3346,
        "ko": 34
    },
    "percentiles4": {
        "total": 3609,
        "ok": 3683,
        "ko": 46
    },
    "group1": {
    "name": "t < 250 ms",
    "htmlName": "t < 250 ms",
    "count": 8028,
    "percentage": 20
},
    "group2": {
    "name": "250 ms <= t < 1200 ms",
    "htmlName": "t >= 250 ms <br> t < 1200 ms",
    "count": 8274,
    "percentage": 21
},
    "group3": {
    "name": "t >= 1200 ms",
    "htmlName": "t >= 1200 ms",
    "count": 16431,
    "percentage": 41
},
    "group4": {
    "name": "failed",
    "htmlName": "failed",
    "count": 6927,
    "percentage": 17
},
    "meanNumberOfRequestsPerSecond": {
        "total": 160.5668016194332,
        "ok": 132.52226720647772,
        "ko": 28.044534412955464
    }
}
    },"req_cre-ditos-1306955929": {
        "type": "REQUEST",
        "name": "créditos",
"path": "créditos",
"pathFormatted": "req_cre-ditos-1306955929",
"stats": {
    "name": "créditos",
    "numberOfRequests": {
        "total": 19860,
        "ok": 15279,
        "ko": 4581
    },
    "minResponseTime": {
        "total": 0,
        "ok": 3,
        "ko": 0
    },
    "maxResponseTime": {
        "total": 4217,
        "ok": 4217,
        "ko": 3235
    },
    "meanResponseTime": {
        "total": 1077,
        "ok": 1396,
        "ko": 11
    },
    "standardDeviation": {
        "total": 1196,
        "ok": 1189,
        "ko": 49
    },
    "percentiles1": {
        "total": 600,
        "ok": 1154,
        "ko": 6
    },
    "percentiles2": {
        "total": 2119,
        "ok": 2516,
        "ko": 16
    },
    "percentiles3": {
        "total": 3285,
        "ok": 3351,
        "ko": 33
    },
    "percentiles4": {
        "total": 3585,
        "ok": 3636,
        "ko": 43
    },
    "group1": {
    "name": "t < 250 ms",
    "htmlName": "t < 250 ms",
    "count": 3920,
    "percentage": 20
},
    "group2": {
    "name": "250 ms <= t < 1200 ms",
    "htmlName": "t >= 250 ms <br> t < 1200 ms",
    "count": 3916,
    "percentage": 20
},
    "group3": {
    "name": "t >= 1200 ms",
    "htmlName": "t >= 1200 ms",
    "count": 7443,
    "percentage": 37
},
    "group4": {
    "name": "failed",
    "htmlName": "failed",
    "count": 4581,
    "percentage": 23
},
    "meanNumberOfRequestsPerSecond": {
        "total": 80.40485829959515,
        "ok": 61.8582995951417,
        "ko": 18.546558704453442
    }
}
    }
}

}